{"version":1,"resource":"file:///home/artur/Projects/simulat/txt/data.py","entries":[{"id":"SLh7.py","timestamp":1653401162003},{"id":"vt4M.py","timestamp":1653401399019},{"id":"d59M.py","timestamp":1653401410739},{"id":"UGYJ.py","timestamp":1653401469473},{"id":"a2P0.py","timestamp":1653401525713},{"id":"aSbo.py","timestamp":1653401540596},{"id":"7aT9.py","timestamp":1653401594163},{"id":"ZEcI.py","timestamp":1653401657119},{"id":"gRMr.py","timestamp":1653401760289},{"id":"9xu5.py","timestamp":1653401791299},{"id":"lTwr.py","timestamp":1653401806999},{"id":"0hir.py","timestamp":1653401876536},{"id":"Nvwe.py","timestamp":1653402005646},{"id":"JbY3.py","timestamp":1653402380016},{"id":"ucbz.py","timestamp":1653402396429},{"id":"zWtA.py","source":"renamed.source","timestamp":1653402566694},{"id":"2RcC.py","timestamp":1653404263806},{"id":"WPlW.py","timestamp":1653486440103},{"id":"4aaF.py","timestamp":1653487073103},{"id":"cunV.py","timestamp":1653487503260},{"id":"MQ14.py","timestamp":1653494302672},{"id":"rT3D.py","timestamp":1654352432240},{"id":"j7Nt.py","timestamp":1654352580065},{"id":"asSN.py","timestamp":1654352600604},{"id":"QWLG.py","source":"undoRedo.source","timestamp":1654352662373},{"id":"kDL6.py","timestamp":1654701558671},{"id":"iADs.py","source":"renamed.source","timestamp":1654701696838},{"id":"SAo2.py","timestamp":1654717286848},{"id":"trtB.py","timestamp":1654717538932},{"id":"DHJK.py","timestamp":1655476903789},{"id":"hjLm.py","timestamp":1655479205272},{"id":"TxPV.py","timestamp":1655480948200},{"id":"vgxA.py","timestamp":1655481141002},{"id":"cG54.py","timestamp":1655481389573},{"id":"KAEs.py","timestamp":1655481465775},{"id":"BZUj.py","timestamp":1655481545755},{"id":"z8Vf.py","timestamp":1655481556058},{"id":"cHJQ.py","timestamp":1655482203536},{"id":"O4Lo.py","timestamp":1655484046385},{"id":"t9QC.py","timestamp":1655484057102},{"id":"HEaH.py","timestamp":1655484467489}]}